pocli/__init__.py
pocli/cli.py
pocli/lib.py
pocli-0.1.11.data/scripts/ocpasswd.bash
pocli-0.1.11.dist-info/LICENSE
pocli-0.1.11.dist-info/METADATA
pocli-0.1.11.dist-info/WHEEL
pocli-0.1.11.dist-info/entry_points.txt
pocli-0.1.11.dist-info/top_level.txt
pocli-0.1.11.dist-info/RECORD
