Metadata-Version: 2.1
Name: pocli
Version: 0.1.11
Summary: Python-based command-line client for OwnCloud
Home-page: UNKNOWN
Author: Florian Kaiser, Klaus Reuter
Author-email: klaus.reuter@gmail.com
License: UNKNOWN
Platform: UNKNOWN
Requires-Dist: six
Requires-Dist: pyocclient
